RISC/RISC_top.v
module MIPS32_PIP( 
    clk1, clk2
);

    input clk1,clk2;
    reg [31:0] PC, IF_ID_NPC, IF_ID_IR;
    reg [31:0] ID_EX_NPC, ID_EX_A, ID_EX_B, ID_EX_IMM, ID_EX_IR;
    reg [2:0] ID_EX_TYPE, EX_MEM_TYPE, MEM_WB_TYPE;
    reg [31:0] EX_MEM_COND, EX_MEM_ALUout, EX_MEM_B, EX_MEM_IR ;
    reg [31:0] MEM_WB_LMD, MEM_WB_ALUout, MEM_WB_IR;

    reg [31:0] Reg [0:31];
    reg [31:0] Mem [0:1023];

    reg HLTDT;
    reg BRDT;

    parameter ADD=6'b000000, SUB=6'b000001, AND=6'b000010, OR=6'b000011, SLT=6'b000100, MUL=6'b000101, HLT=6'b111111, LW=6'b001000, SW=6'b001001, ADDI=6'b001010, SUBI=6'b001011, SLTI=6'b001100, BNEQZ=6'b001101, BEQZ=6'b001110;
    parameter RR_ALU=3'h0, RM_ALU=3'h1, LOAD=3'h2, STORE=3'h3, BRANCH=3'h4, HALT=3'h5;

    //IF STAGE
    always @(posedge clk1) begin
        if(!HLTDT) begin
            if((EX_MEM_IR[31:26]==BEQZ && EX_MEM_COND==1)||(EX_MEM_IR[31:26]==BNEQZ && EX_MEM_COND==0)) begin
                BRDT <= #1 1;
                IF_ID_IR <= #1 Mem[EX_MEM_ALUout];
                IF_ID_NPC <= #1 EX_MEM_ALUout;
                PC <= #1 EX_MEM_ALUout;
            end
            else begin
                IF_ID_IR <= #1 Mem[PC];
                IF_ID_NPC <= #1 PC+1;
                PC <= #1 PC+1; 
            end
        end
    end

    //ID STAGE
    always @(posedge clk2) begin
        if(!HLTDT) begin
            ID_EX_NPC <= #1 IF_ID_NPC;
            ID_EX_IR <= #1 IF_ID_IR;
            ID_EX_IMM <= #1 {{16{IF_ID_IR[15]}},{IF_ID_IR[15:0]}};

            ID_EX_A <= #1 Reg[IF_ID_IR[25:21]];
            ID_EX_B <= #1 Reg[IF_ID_IR[20:16]];

            #1 case (IF_ID_IR[31:26])
                ADD,SUB,AND,OR,SLT,MUL : ID_EX_TYPE <= RR_ALU;
                ADDI,SUBI,SLTI : ID_EX_TYPE <= RM_ALU;
                HLT : ID_EX_TYPE <= HALT;
                LW : ID_EX_TYPE <= LOAD;
                SW : ID_EX_TYPE <= STORE;
                BEQZ,BNEQZ : ID_EX_TYPE <= BRANCH;
                default: ID_EX_TYPE <= HALT;
            endcase 

        end
    end 

    //EX STAGE
    always @(posedge clk1) begin
        if(!HLTDT) begin
            EX_MEM_B <= #1 ID_EX_B;
            EX_MEM_TYPE <= #1 ID_EX_TYPE;
            EX_MEM_IR <= #1 ID_EX_IR;
            BRDT <= #1 0;

            EX_MEM_COND <= #1 !ID_EX_A;

            #1 case (ID_EX_TYPE)
                RR_ALU : begin
                            case(ID_EX_IR[31:26])
                                ADD : EX_MEM_ALUout <= ID_EX_A + ID_EX_B;
                                SUB : EX_MEM_ALUout <= ID_EX_A - ID_EX_B;
                                AND : EX_MEM_ALUout <= ID_EX_A & ID_EX_B;
                                OR : EX_MEM_ALUout <= ID_EX_A | ID_EX_B;
                                SLT : EX_MEM_ALUout <= ID_EX_A < ID_EX_B;
                                MUL : EX_MEM_ALUout <= ID_EX_A * ID_EX_B;
                                default : EX_MEM_ALUout <= 32'hxxxxxxxx;
                            endcase
                        end
                RM_ALU : begin
                            case(ID_EX_IR[31:26])
                                ADDI : EX_MEM_ALUout <= ID_EX_A + ID_EX_IMM;
                                SUBI : EX_MEM_ALUout <= ID_EX_A - ID_EX_IMM;
                                SLTI : EX_MEM_ALUout <= ID_EX_A < ID_EX_IMM;
                                default : EX_MEM_ALUout <= 32'hxxxxxxxx;
                            endcase
                        end
                LOAD, STORE : EX_MEM_ALUout <= ID_EX_A + ID_EX_IMM;
                BRANCH : EX_MEM_ALUout <= ID_EX_NPC + ID_EX_IMM;
            endcase 

        end
    end


    //MEM STAGE
    always @(posedge clk2) begin
        if(!HLTDT) begin
            MEM_WB_TYPE <= #1 EX_MEM_TYPE;
            MEM_WB_IR <= #1 EX_MEM_IR;

            #1 case(EX_MEM_TYPE)
                RR_ALU,RM_ALU : MEM_WB_ALUout <= EX_MEM_ALUout;
                LOAD : MEM_WB_LMD <= Mem[EX_MEM_ALUout]; 
                STORE : if(!BRDT) Mem[EX_MEM_ALUout] <= EX_MEM_B;
            endcase
        end
    end 

    //WB STAGE
    always @(posedge clk1) begin
        if(!BRDT) begin
            #1 case(MEM_WB_TYPE)
                RR_ALU : Reg[MEM_WB_IR[15:11]] <= MEM_WB_ALUout;
                RM_ALU : Reg[MEM_WB_IR[20:16]] <= MEM_WB_ALUout;
                LOAD : Reg[MEM_WB_IR[20:16]] <= MEM_WB_LMD;
                HALT : HLTDT <= 1;
            endcase
        end
    end 

endmodule

RISC/RISC_top_tb.v
`include "RISC_top.v"

module MIPS32_PIP_tb();

    reg clk1,clk2;
    integer k;  

    MIPS32_PIP DUT(clk1,clk2);

    initial begin
        repeat(20) begin
            clk1 = 0; clk2 = 0;
            #5 clk1 = 1; #5 clk1 = 0;
            #5 clk2 = 1; #5 clk2 = 0;
        end
    end

    initial begin
        for (k=0; k<20; k++) begin
            DUT.Reg[k] = k;
        end

        DUT.Mem[0] = 32'h2801000a; //ADDI R1 R0 10
        DUT.Mem[1] = 32'h28020014; //ADDI R2 R0 20
        DUT.Mem[2] = 32'h28030019; //ADDI R3 R0 25
        DUT.Mem[3] = 32'h0ce77800; //OR R7 R7 R7
        DUT.Mem[4] = 32'h0ce77800; //OR R7 R7 R7
        DUT.Mem[5] = 32'h00222000; //ADD R4 R1 R2
        DUT.Mem[6] = 32'h0ce77800; //OR R7 R7 R7
        DUT.Mem[7] = 32'h00832800; //ADD R5 R4 R3
        DUT.Mem[8] = 32'hfc000000; //HLT

        DUT.HLTDT = 0;
        DUT.PC = 0;
        DUT.BRDT = 0;

        #280
        for (k=0; k<6; k++) begin
            $display("R%1d - %2d", k, DUT.Reg[k]);
        end
    end

    initial begin
        $dumpfile("pip.vcd");
        $dumpvars(0,MIPS32_PIP_tb);
        #300 $finish;
    end


endmodule

RISC/pip.vcd
$date
	Sat Jun 01 07:44:55 2024
$end
$version
	Icarus Verilog
$end
$timescale
	1s
$end
$scope module MIPS32_PIP_tb $end
$var reg 1 ! clk1 $end
$var reg 1 " clk2 $end
$var integer 32 # k [31:0] $end
$scope module DUT $end
$var wire 1 ! clk1 $end
$var wire 1 " clk2 $end
$var parameter 6 $ ADD $end
$var parameter 6 % ADDI $end
$var parameter 6 & AND $end
$var parameter 6 ' BEQZ $end
$var parameter 6 ( BNEQZ $end
$var parameter 3 ) BRANCH $end
$var parameter 3 * HALT $end
$var parameter 6 + HLT $end
$var parameter 3 , LOAD $end
$var parameter 6 - LW $end
$var parameter 6 . MUL $end
$var parameter 6 / OR $end
$var parameter 3 0 RM_ALU $end
$var parameter 3 1 RR_ALU $end
$var parameter 6 2 SLT $end
$var parameter 6 3 SLTI $end
$var parameter 3 4 STORE $end
$var parameter 6 5 SUB $end
$var parameter 6 6 SUBI $end
$var parameter 6 7 SW $end
$var reg 1 8 BRDT $end
$var reg 32 9 EX_MEM_ALUout [31:0] $end
$var reg 32 : EX_MEM_B [31:0] $end
$var reg 32 ; EX_MEM_COND [31:0] $end
$var reg 32 < EX_MEM_IR [31:0] $end
$var reg 3 = EX_MEM_TYPE [2:0] $end
$var reg 1 > HLTDT $end
$var reg 32 ? ID_EX_A [31:0] $end
$var reg 32 @ ID_EX_B [31:0] $end
$var reg 32 A ID_EX_IMM [31:0] $end
$var reg 32 B ID_EX_IR [31:0] $end
$var reg 32 C ID_EX_NPC [31:0] $end
$var reg 3 D ID_EX_TYPE [2:0] $end
$var reg 32 E IF_ID_IR [31:0] $end
$var reg 32 F IF_ID_NPC [31:0] $end
$var reg 32 G MEM_WB_ALUout [31:0] $end
$var reg 32 H MEM_WB_IR [31:0] $end
$var reg 32 I MEM_WB_LMD [31:0] $end
$var reg 3 J MEM_WB_TYPE [2:0] $end
$var reg 32 K PC [31:0] $end
$upscope $end
$upscope $end
$enddefinitions $end
$comment Show the parameter values. $end
$dumpall
b1001 7
b1011 6
b1 5
b11 4
b1100 3
b100 2
b0 1
b1 0
b11 /
b101 .
b1000 -
b10 ,
b111111 +
b101 *
b100 )
b1101 (
b1110 '
b10 &
b1010 %
b0 $
$end
#0
$dumpvars
b0 K
bx J
bx I
bx H
bx G
bx F
bx E
bx D
bx C
bx B
bx A
bx @
bx ?
0>
bx =
bx <
bx ;
bx :
bx 9
08
b10100 #
0"
0!
$end
#5
1!
#6
b1 K
b1 F
b101000000000010000000000001010 E
b0x ;
#10
0!
#15
1"
#16
b1 D
b1 @
b0 ?
b1010 A
b101000000000010000000000001010 B
b1 C
#20
0"
#25
1!
#26
b1010 9
b10 K
b10 F
b101000000000100000000000010100 E
b1 ;
b101000000000010000000000001010 <
b1 =
b1 :
#30
0!
#35
1"
#36
b1010 G
b101000000000010000000000001010 H
b1 J
b10 @
b10100 A
b101000000000100000000000010100 B
b10 C
#40
0"
#45
1!
#46
b10100 9
b11 K
b11 F
b101000000000110000000000011001 E
b101000000000100000000000010100 <
b10 :
#50
0!
#55
1"
#56
b10100 G
b11 @
b11001 A
b101000000000110000000000011001 B
b11 C
b101000000000100000000000010100 H
#60
0"
#65
1!
#66
b11001 9
b100 K
b100 F
b1100111001110111100000000000 E
b101000000000110000000000011001 <
b11 :
#70
0!
#75
1"
#76
b11001 G
b0 D
b101000000000110000000000011001 H
b111 @
b111 ?
b111100000000000 A
b1100111001110111100000000000 B
b100 C
#80
0"
#85
1!
#86
b111 9
b101 K
b101 F
b0 ;
b1100111001110111100000000000 <
b0 =
b111 :
#90
0!
#95
1"
#96
b111 G
b101 C
b1100111001110111100000000000 H
b0 J
#100
0"
#105
1!
#106
b110 K
b110 F
b1000100010000000000000 E
#110
0!
#115
1"
#116
b10100 @
b1010 ?
b10000000000000 A
b1000100010000000000000 B
b110 C
#120
0"
#125
1!
#126
b11110 9
b111 K
b111 F
b1100111001110111100000000000 E
b1000100010000000000000 <
b10100 :
#130
0!
#135
1"
#136
b11110 G
b111 @
b111 ?
b111100000000000 A
b1100111001110111100000000000 B
b111 C
b1000100010000000000000 H
#140
0"
#145
1!
#146
b111 9
b1000 K
b1000 F
b100000110010100000000000 E
b1100111001110111100000000000 <
b111 :
#150
0!
#155
1"
#156
b111 G
b1100111001110111100000000000 H
b11001 @
b11110 ?
b10100000000000 A
b100000110010100000000000 B
b1000 C
#160
0"
#165
1!
#166
b110111 9
b1001 K
b1001 F
b11111100000000000000000000000000 E
b100000110010100000000000 <
b11001 :
#170
0!
#175
1"
#176
b101 D
b110111 G
b0 @
b0 ?
b0 A
b11111100000000000000000000000000 B
b1001 C
b100000110010100000000000 H
#180
0"
#185
1!
#186
b1010 K
b1010 F
bx E
b1 ;
b11111100000000000000000000000000 <
b101 =
b0 :
#190
0!
#195
1"
#196
b11111100000000000000000000000000 H
b101 J
bx @
bx ?
bx A
bx B
b1010 C
#200
0"
#205
1!
#206
1>
b1011 K
b1011 F
b0x ;
bx <
bx :
#210
0!
#215
1"
#220
0"
#225
1!
#230
0!
#235
1"
#240
0"
#245
1!
#250
0!
#255
1"
#260
0"
#265
1!
#270
0!
#275
1"
#280
0"
b110 #
